tentacle/__init__.py
tentacle/__init__.py.bak
tentacle/events.py
tentacle/events.py.bak
tentacle/overlay.py
tentacle/overlay.py.bak
tentacle/switchboard (conflicted copy 2023-01-09 140222).py
tentacle/switchboard.py
tentacle/switchboard.py.bak
tentacle/tcl.py
tentacle/tcl.py.bak
tentacle/tcl_blender.py
tentacle/tcl_blender.py.bak
tentacle/tcl_max.py
tentacle/tcl_max.py.bak
tentacle/tcl_maya.py
tentacle/tcl_maya.py.bak
tentacle/slots/__init__.py
tentacle/slots/animation.py
tentacle/slots/cameras.py
tentacle/slots/convert.py
tentacle/slots/crease.py
tentacle/slots/create.py
tentacle/slots/deformation.py
tentacle/slots/display.py
tentacle/slots/duplicate.py
tentacle/slots/dynLayout.py
tentacle/slots/edit.py
tentacle/slots/editors.py
tentacle/slots/file.py
tentacle/slots/init.py
tentacle/slots/lighting.py
tentacle/slots/main.py
tentacle/slots/materials.py
tentacle/slots/mirror.py
tentacle/slots/normals.py
tentacle/slots/nurbs.py
tentacle/slots/pivot.py
tentacle/slots/polygons.py
tentacle/slots/preferences.py
tentacle/slots/rendering.py
tentacle/slots/rigging.py
tentacle/slots/scene.py
tentacle/slots/scripting.py
tentacle/slots/selection.py
tentacle/slots/subdivision.py
tentacle/slots/symmetry.py
tentacle/slots/transform.py
tentacle/slots/utilities.py
tentacle/slots/uv.py
tentacle/slots/vfx.py
tentacle/slots/blender/__init__.py
tentacle/slots/blender/animation_blender.py
tentacle/slots/blender/cameras_blender.py
tentacle/slots/blender/convert_blender.py
tentacle/slots/blender/crease_blender.py
tentacle/slots/blender/create_blender.py
tentacle/slots/blender/deformation_blender.py
tentacle/slots/blender/display_blender.py
tentacle/slots/blender/duplicate_blender.py
tentacle/slots/blender/dynLayout_blender.py
tentacle/slots/blender/edit_blender.py
tentacle/slots/blender/editors_blender.py
tentacle/slots/blender/file_blender.py
tentacle/slots/blender/init_blender.py
tentacle/slots/blender/lighting_blender.py
tentacle/slots/blender/main_blender.py
tentacletk-0.511.dist-info/METADATA
tentacletk-0.511.dist-info/WHEEL
tentacletk-0.511.dist-info/top_level.txt
tentacletk-0.511.dist-info/RECORD
